{
    "graph": {
        "nodes": {
            "0": {
                "ref": "conanfile",
                "id": "0",
                "recipe": "Consumer",
                "package_id": null,
                "prev": null,
                "rrev": null,
                "rrev_timestamp": null,
                "prev_timestamp": null,
                "remote": null,
                "binary_remote": null,
                "build_id": null,
                "binary": null,
                "invalid_build": false,
                "info_invalid": null,
                "name": null,
                "user": null,
                "channel": null,
                "url": null,
                "license": null,
                "author": null,
                "description": null,
                "homepage": null,
                "build_policy": null,
                "upload_policy": null,
                "revision_mode": "hash",
                "provides": null,
                "deprecated": null,
                "win_bash": null,
                "win_bash_run": null,
                "default_options": null,
                "options_description": null,
                "version": null,
                "topics": null,
                "package_type": "unknown",
                "languages": [],
                "settings": {
                    "os": "Linux",
                    "arch": "x86_64",
                    "compiler": "gcc",
                    "compiler.cppstd": "gnu17",
                    "compiler.libcxx": "libstdc++11",
                    "compiler.version": "14",
                    "build_type": "Release"
                },
                "options": {},
                "options_definitions": {},
                "generators": [
                    "CMakeDeps",
                    "CMakeToolchain"
                ],
                "python_requires": null,
                "system_requires": {},
                "recipe_folder": null,
                "source_folder": null,
                "build_folder": null,
                "generators_folder": null,
                "package_folder": null,
                "immutable_package_folder": null,
                "cpp_info": {
                    "root": {
                        "includedirs": [
                            "include"
                        ],
                        "srcdirs": null,
                        "libdirs": [
                            "lib"
                        ],
                        "resdirs": null,
                        "bindirs": [
                            "bin"
                        ],
                        "builddirs": null,
                        "frameworkdirs": null,
                        "system_libs": null,
                        "frameworks": null,
                        "libs": null,
                        "defines": null,
                        "cflags": null,
                        "cxxflags": null,
                        "sharedlinkflags": null,
                        "exelinkflags": null,
                        "objects": null,
                        "sources": null,
                        "sysroot": null,
                        "requires": null,
                        "properties": null,
                        "exe": null,
                        "type": null,
                        "location": null,
                        "link_location": null,
                        "languages": null
                    }
                },
                "conf_info": {},
                "label": "conanfile.txt",
                "vendor": false,
                "dependencies": {
                    "1": {
                        "ref": "hello_lib/1.0",
                        "require": "hello_lib/1.0",
                        "run": false,
                        "libs": true,
                        "skip": false,
                        "test": false,
                        "force": false,
                        "direct": true,
                        "build": false,
                        "transitive_headers": null,
                        "transitive_libs": null,
                        "headers": true,
                        "package_id_mode": null,
                        "visible": true
                    },
                    "2": {
                        "ref": "fmt/11.0.2",
                        "require": "fmt/11.0.2",
                        "run": false,
                        "libs": true,
                        "skip": false,
                        "test": false,
                        "force": false,
                        "direct": false,
                        "build": false,
                        "transitive_headers": null,
                        "transitive_libs": null,
                        "headers": true,
                        "package_id_mode": null,
                        "visible": true
                    }
                },
                "context": "host",
                "test": false
            },
            "1": {
                "ref": "hello_lib/1.0#7cf9e80375da4bedb00c9718596ea5f9",
                "id": "1",
                "recipe": "Cache",
                "package_id": "c6ee1fe620928d3f4b048e15b45421eab9b6cdca",
                "prev": "a067347826c3d93be1bbc172ac85f75b",
                "rrev": "7cf9e80375da4bedb00c9718596ea5f9",
                "rrev_timestamp": 1774499072.5643857,
                "prev_timestamp": 1774448358.4931846,
                "remote": null,
                "binary_remote": null,
                "build_id": null,
                "binary": "Cache",
                "invalid_build": false,
                "info_invalid": null,
                "name": "hello_lib",
                "user": null,
                "channel": null,
                "url": null,
                "license": null,
                "author": null,
                "description": null,
                "homepage": null,
                "build_policy": null,
                "upload_policy": null,
                "revision_mode": "hash",
                "provides": null,
                "deprecated": null,
                "win_bash": null,
                "win_bash_run": null,
                "default_options": null,
                "options_description": null,
                "version": "1.0",
                "topics": null,
                "package_type": "unknown",
                "languages": [],
                "settings": {
                    "os": "Linux",
                    "arch": "x86_64",
                    "compiler": "gcc",
                    "compiler.cppstd": "gnu17",
                    "compiler.libcxx": "libstdc++11",
                    "compiler.version": "14",
                    "build_type": "Release"
                },
                "options": {},
                "options_definitions": {},
                "generators": [
                    "CMakeDeps",
                    "CMakeToolchain"
                ],
                "python_requires": null,
                "system_requires": {},
                "recipe_folder": "/home/jegan/.conan2/p/hello4118bf2851ea8/e",
                "source_folder": null,
                "build_folder": null,
                "generators_folder": null,
                "package_folder": null,
                "immutable_package_folder": null,
                "cpp_info": {
                    "root": {
                        "includedirs": [
                            "include"
                        ],
                        "srcdirs": null,
                        "libdirs": [
                            "lib"
                        ],
                        "resdirs": null,
                        "bindirs": [
                            "bin"
                        ],
                        "builddirs": null,
                        "frameworkdirs": null,
                        "system_libs": null,
                        "frameworks": null,
                        "libs": null,
                        "defines": null,
                        "cflags": null,
                        "cxxflags": null,
                        "sharedlinkflags": null,
                        "exelinkflags": null,
                        "objects": null,
                        "sources": null,
                        "sysroot": null,
                        "requires": null,
                        "properties": null,
                        "exe": null,
                        "type": null,
                        "location": null,
                        "link_location": null,
                        "languages": null
                    }
                },
                "conf_info": {},
                "label": "hello_lib/1.0",
                "info": {
                    "settings": {
                        "os": "Linux",
                        "arch": "x86_64",
                        "compiler": "gcc",
                        "compiler.cppstd": "gnu17",
                        "compiler.libcxx": "libstdc++11",
                        "compiler.version": "14",
                        "build_type": "Release"
                    },
                    "requires": [
                        "fmt/11.Y.Z"
                    ]
                },
                "vendor": false,
                "dependencies": {
                    "2": {
                        "ref": "fmt/11.0.2",
                        "require": "fmt/11.0.2",
                        "run": false,
                        "libs": true,
                        "skip": false,
                        "test": false,
                        "force": false,
                        "direct": true,
                        "build": false,
                        "transitive_headers": null,
                        "transitive_libs": null,
                        "headers": true,
                        "package_id_mode": "semver_mode",
                        "visible": true
                    }
                },
                "context": "host",
                "test": false
            },
            "2": {
                "ref": "fmt/11.0.2#b4a24d70b93466b9b508ddb7b014643b",
                "id": "2",
                "recipe": "Cache",
                "package_id": "e1a00a27429c64710e1cdc152f52b904c7a9d14a",
                "prev": "a6c17b3fbf3daeac59dfcbbd9092385f",
                "rrev": "b4a24d70b93466b9b508ddb7b014643b",
                "rrev_timestamp": 1735899162.196,
                "prev_timestamp": 1774429928.0301821,
                "remote": null,
                "binary_remote": null,
                "build_id": null,
                "binary": "Cache",
                "invalid_build": false,
                "info_invalid": null,
                "name": "fmt",
                "user": null,
                "channel": null,
                "url": "https://github.com/conan-io/conan-center-index",
                "license": "MIT",
                "author": null,
                "description": "A safe and fast alternative to printf and IOStreams.",
                "homepage": "https://github.com/fmtlib/fmt",
                "build_policy": null,
                "upload_policy": null,
                "revision_mode": "hash",
                "provides": null,
                "deprecated": null,
                "win_bash": null,
                "win_bash_run": null,
                "default_options": {
                    "header_only": false,
                    "shared": false,
                    "fPIC": true,
                    "with_fmt_alias": false,
                    "with_os_api": true,
                    "with_unicode": true
                },
                "options_description": null,
                "version": "11.0.2",
                "topics": [
                    "format",
                    "iostream",
                    "printf"
                ],
                "package_type": "static-library",
                "languages": [],
                "settings": {
                    "os": "Linux",
                    "arch": "x86_64",
                    "compiler": "gcc",
                    "compiler.cppstd": "gnu17",
                    "compiler.libcxx": "libstdc++11",
                    "compiler.version": "14",
                    "build_type": "Release"
                },
                "options": {
                    "fPIC": "True",
                    "header_only": "False",
                    "shared": "False",
                    "with_fmt_alias": "False",
                    "with_os_api": "True",
                    "with_unicode": "True"
                },
                "options_definitions": {
                    "header_only": [
                        "True",
                        "False"
                    ],
                    "shared": [
                        "True",
                        "False"
                    ],
                    "fPIC": [
                        "True",
                        "False"
                    ],
                    "with_fmt_alias": [
                        "True",
                        "False"
                    ],
                    "with_os_api": [
                        "True",
                        "False"
                    ],
                    "with_unicode": [
                        "True",
                        "False"
                    ]
                },
                "generators": [],
                "python_requires": null,
                "system_requires": {},
                "recipe_folder": "/home/jegan/.conan2/p/fmt0f3bd0ff361a1/e",
                "source_folder": null,
                "build_folder": null,
                "generators_folder": null,
                "package_folder": null,
                "immutable_package_folder": null,
                "cpp_info": {
                    "root": {
                        "includedirs": [
                            "include"
                        ],
                        "srcdirs": null,
                        "libdirs": [
                            "lib"
                        ],
                        "resdirs": null,
                        "bindirs": [
                            "bin"
                        ],
                        "builddirs": null,
                        "frameworkdirs": null,
                        "system_libs": null,
                        "frameworks": null,
                        "libs": null,
                        "defines": null,
                        "cflags": null,
                        "cxxflags": null,
                        "sharedlinkflags": null,
                        "exelinkflags": null,
                        "objects": null,
                        "sources": null,
                        "sysroot": null,
                        "requires": null,
                        "properties": null,
                        "exe": null,
                        "type": null,
                        "location": null,
                        "link_location": null,
                        "languages": null
                    }
                },
                "conf_info": {},
                "label": "fmt/11.0.2",
                "info": {
                    "settings": {
                        "os": "Linux",
                        "arch": "x86_64",
                        "compiler": "gcc",
                        "compiler.cppstd": "gnu17",
                        "compiler.libcxx": "libstdc++11",
                        "compiler.version": "14",
                        "build_type": "Release"
                    },
                    "options": {
                        "fPIC": "True",
                        "header_only": "False",
                        "shared": "False",
                        "with_os_api": "True",
                        "with_unicode": "True"
                    }
                },
                "vendor": false,
                "conandata": {
                    "sources": {
                        "11.0.2": {
                            "sha256": "40fc58bebcf38c759e11a7bd8fdc163507d2423ef5058bba7f26280c5b9c5465",
                            "url": "https://github.com/fmtlib/fmt/releases/download/11.0.2/fmt-11.0.2.zip"
                        }
                    }
                },
                "dependencies": {},
                "context": "host",
                "test": false
            }
        },
        "root": {
            "0": "None"
        },
        "overrides": {},
        "resolved_ranges": {},
        "replaced_requires": {},
        "error": null
    }
}
